<annotation>
	<folder>tmp_selected</folder>
	<filename>754img2.jpg</filename>
	<path>C:\Users\zenier\Downloads\Fall Detection\FallDataset\tmp_selected\754img2.jpg</path>
	<source>
		<database>Unknown</database>
	</source>
	<size>
		<width>320</width>
		<height>240</height>
		<depth>3</depth>
	</size>
	<segmented>0</segmented>
	<object>
		<name>FellDown</name>
		<pose>Unspecified</pose>
		<truncated>0</truncated>
		<difficult>0</difficult>
		<bndbox>
			<xmin>73</xmin>
			<ymin>148</ymin>
			<xmax>205</xmax>
			<ymax>209</ymax>
		</bndbox>
	</object>
</annotation>
